{
  "version": "1.0",
  "provenance": {
    "contentHash": "normalized-content-hash",
    "irHash": "f6488ad8fbd6e013d101e9cf7f847b318ebbd8e0335732f9e0ea4768b2ba215f",
    "compilerVersion": "0.0.0",
    "schemaVersion": "1.0",
    "compiledAt": "2024-01-01T00:00:00.000Z"
  },
  "modules": [],
  "entities": [
    {
      "name": "WorkflowInstance",
      "properties": [
        {
          "name": "id",
          "type": {
            "name": "string",
            "nullable": false
          },
          "modifiers": [
            "required"
          ]
        },
        {
          "name": "name",
          "type": {
            "name": "string",
            "nullable": false
          },
          "modifiers": [
            "required"
          ]
        },
        {
          "name": "version",
          "type": {
            "name": "string",
            "nullable": false
          },
          "modifiers": [
            "required"
          ]
        },
        {
          "name": "status",
          "type": {
            "name": "string",
            "nullable": false
          },
          "defaultValue": {
            "kind": "string",
            "value": "active"
          },
          "modifiers": [
            "required"
          ]
        },
        {
          "name": "createdBy",
          "type": {
            "name": "string",
            "nullable": false
          },
          "modifiers": [
            "required"
          ]
        },
        {
          "name": "createdAt",
          "type": {
            "name": "string",
            "nullable": false
          },
          "defaultValue": {
            "kind": "string",
            "value": ""
          },
          "modifiers": []
        },
        {
          "name": "updatedAt",
          "type": {
            "name": "string",
            "nullable": false
          },
          "defaultValue": {
            "kind": "string",
            "value": ""
          },
          "modifiers": []
        },
        {
          "name": "isLocked",
          "type": {
            "name": "boolean",
            "nullable": false
          },
          "defaultValue": {
            "kind": "boolean",
            "value": false
          },
          "modifiers": []
        },
        {
          "name": "concurrencyVersion",
          "type": {
            "name": "number",
            "nullable": false
          },
          "defaultValue": {
            "kind": "number",
            "value": 1
          },
          "modifiers": []
        }
      ],
      "computedProperties": [],
      "relationships": [],
      "commands": [
        "pause",
        "resume",
        "lock",
        "unlock",
        "complete"
      ],
      "constraints": [
        {
          "name": "versionRequired",
          "code": "versionRequired",
          "expression": {
            "kind": "binary",
            "operator": "!=",
            "left": {
              "kind": "member",
              "object": {
                "kind": "identifier",
                "name": "self"
              },
              "property": "version"
            },
            "right": {
              "kind": "literal",
              "value": {
                "kind": "string",
                "value": ""
              }
            }
          },
          "severity": "block",
          "message": "Version must be provided",
          "overrideable": false
        },
        {
          "name": "statusValid",
          "code": "statusValid",
          "expression": {
            "kind": "binary",
            "operator": "in",
            "left": {
              "kind": "member",
              "object": {
                "kind": "identifier",
                "name": "self"
              },
              "property": "status"
            },
            "right": {
              "kind": "array",
              "elements": [
                {
                  "kind": "literal",
                  "value": {
                    "kind": "string",
                    "value": "active"
                  }
                },
                {
                  "kind": "literal",
                  "value": {
                    "kind": "string",
                    "value": "paused"
                  }
                },
                {
                  "kind": "literal",
                  "value": {
                    "kind": "string",
                    "value": "completed"
                  }
                },
                {
                  "kind": "literal",
                  "value": {
                    "kind": "string",
                    "value": "cancelled"
                  }
                }
              ]
            }
          },
          "severity": "block",
          "message": "Status must be valid",
          "overrideable": false
        },
        {
          "name": "severityHighConcurrency",
          "code": "severityHighConcurrency",
          "expression": {
            "kind": "binary",
            "operator": ">",
            "left": {
              "kind": "member",
              "object": {
                "kind": "identifier",
                "name": "self"
              },
              "property": "concurrencyVersion"
            },
            "right": {
              "kind": "literal",
              "value": {
                "kind": "number",
                "value": 10
              }
            }
          },
          "severity": "warn",
          "message": "Warning: High concurrency version detected",
          "overrideable": false
        }
      ],
      "policies": []
    }
  ],
  "stores": [
    {
      "entity": "WorkflowInstance",
      "target": "memory",
      "config": {}
    }
  ],
  "events": [
    {
      "name": "WorkflowPaused",
      "channel": "workflow.paused",
      "payload": [
        {
          "name": "workflowId",
          "type": {
            "name": "string",
            "nullable": false
          },
          "required": true
        },
        {
          "name": "previousStatus",
          "type": {
            "name": "string",
            "nullable": false
          },
          "required": true
        }
      ]
    },
    {
      "name": "WorkflowResumed",
      "channel": "workflow.resumed",
      "payload": [
        {
          "name": "workflowId",
          "type": {
            "name": "string",
            "nullable": false
          },
          "required": true
        },
        {
          "name": "previousStatus",
          "type": {
            "name": "string",
            "nullable": false
          },
          "required": true
        }
      ]
    },
    {
      "name": "WorkflowLocked",
      "channel": "workflow.locked",
      "payload": [
        {
          "name": "workflowId",
          "type": {
            "name": "string",
            "nullable": false
          },
          "required": true
        },
        {
          "name": "newVersion",
          "type": {
            "name": "number",
            "nullable": false
          },
          "required": true
        }
      ]
    },
    {
      "name": "WorkflowUnlocked",
      "channel": "workflow.unlocked",
      "payload": [
        {
          "name": "workflowId",
          "type": {
            "name": "string",
            "nullable": false
          },
          "required": true
        },
        {
          "name": "newVersion",
          "type": {
            "name": "number",
            "nullable": false
          },
          "required": true
        }
      ]
    },
    {
      "name": "WorkflowCompleted",
      "channel": "workflow.completed",
      "payload": [
        {
          "name": "workflowId",
          "type": {
            "name": "string",
            "nullable": false
          },
          "required": true
        },
        {
          "name": "finalStatus",
          "type": {
            "name": "string",
            "nullable": false
          },
          "required": true
        }
      ]
    }
  ],
  "commands": [
    {
      "name": "pause",
      "entity": "WorkflowInstance",
      "parameters": [],
      "guards": [],
      "constraints": [
        {
          "name": "notLocked",
          "code": "notLocked",
          "expression": {
            "kind": "binary",
            "operator": "==",
            "left": {
              "kind": "member",
              "object": {
                "kind": "identifier",
                "name": "self"
              },
              "property": "isLocked"
            },
            "right": {
              "kind": "literal",
              "value": {
                "kind": "boolean",
                "value": false
              }
            }
          },
          "severity": "block",
          "message": "Workflow instance is locked",
          "overrideable": false
        },
        {
          "name": "canPause",
          "code": "canPause",
          "expression": {
            "kind": "binary",
            "operator": "==",
            "left": {
              "kind": "member",
              "object": {
                "kind": "identifier",
                "name": "self"
              },
              "property": "status"
            },
            "right": {
              "kind": "literal",
              "value": {
                "kind": "string",
                "value": "active"
              }
            }
          },
          "severity": "block",
          "message": "Can only pause active workflows",
          "overrideable": false
        }
      ],
      "actions": [
        {
          "kind": "mutate",
          "target": "status",
          "expression": {
            "kind": "literal",
            "value": {
              "kind": "string",
              "value": "paused"
            }
          }
        },
        {
          "kind": "mutate",
          "target": "updatedAt",
          "expression": {
            "kind": "call",
            "callee": {
              "kind": "identifier",
              "name": "now"
            },
            "args": []
          }
        }
      ],
      "emits": [
        "WorkflowPaused"
      ]
    },
    {
      "name": "resume",
      "entity": "WorkflowInstance",
      "parameters": [],
      "guards": [],
      "constraints": [
        {
          "name": "notLocked",
          "code": "notLocked",
          "expression": {
            "kind": "binary",
            "operator": "==",
            "left": {
              "kind": "member",
              "object": {
                "kind": "identifier",
                "name": "self"
              },
              "property": "isLocked"
            },
            "right": {
              "kind": "literal",
              "value": {
                "kind": "boolean",
                "value": false
              }
            }
          },
          "severity": "block",
          "message": "Workflow instance is locked",
          "overrideable": false
        },
        {
          "name": "canResume",
          "code": "canResume",
          "expression": {
            "kind": "binary",
            "operator": "==",
            "left": {
              "kind": "member",
              "object": {
                "kind": "identifier",
                "name": "self"
              },
              "property": "status"
            },
            "right": {
              "kind": "literal",
              "value": {
                "kind": "string",
                "value": "paused"
              }
            }
          },
          "severity": "block",
          "message": "Can only resume paused workflows",
          "overrideable": false
        }
      ],
      "actions": [
        {
          "kind": "mutate",
          "target": "status",
          "expression": {
            "kind": "literal",
            "value": {
              "kind": "string",
              "value": "active"
            }
          }
        },
        {
          "kind": "mutate",
          "target": "updatedAt",
          "expression": {
            "kind": "call",
            "callee": {
              "kind": "identifier",
              "name": "now"
            },
            "args": []
          }
        }
      ],
      "emits": [
        "WorkflowResumed"
      ]
    },
    {
      "name": "lock",
      "entity": "WorkflowInstance",
      "parameters": [],
      "guards": [],
      "constraints": [
        {
          "name": "notAlreadyLocked",
          "code": "notAlreadyLocked",
          "expression": {
            "kind": "binary",
            "operator": "==",
            "left": {
              "kind": "member",
              "object": {
                "kind": "identifier",
                "name": "self"
              },
              "property": "isLocked"
            },
            "right": {
              "kind": "literal",
              "value": {
                "kind": "boolean",
                "value": false
              }
            }
          },
          "severity": "block",
          "message": "Already locked",
          "overrideable": false
        }
      ],
      "actions": [
        {
          "kind": "mutate",
          "target": "isLocked",
          "expression": {
            "kind": "literal",
            "value": {
              "kind": "boolean",
              "value": true
            }
          }
        },
        {
          "kind": "mutate",
          "target": "concurrencyVersion",
          "expression": {
            "kind": "binary",
            "operator": "+",
            "left": {
              "kind": "member",
              "object": {
                "kind": "identifier",
                "name": "self"
              },
              "property": "concurrencyVersion"
            },
            "right": {
              "kind": "literal",
              "value": {
                "kind": "number",
                "value": 1
              }
            }
          }
        },
        {
          "kind": "mutate",
          "target": "updatedAt",
          "expression": {
            "kind": "call",
            "callee": {
              "kind": "identifier",
              "name": "now"
            },
            "args": []
          }
        }
      ],
      "emits": [
        "WorkflowLocked"
      ]
    },
    {
      "name": "unlock",
      "entity": "WorkflowInstance",
      "parameters": [],
      "guards": [],
      "constraints": [
        {
          "name": "canUnlock",
          "code": "canUnlock",
          "expression": {
            "kind": "binary",
            "operator": "==",
            "left": {
              "kind": "member",
              "object": {
                "kind": "identifier",
                "name": "self"
              },
              "property": "isLocked"
            },
            "right": {
              "kind": "literal",
              "value": {
                "kind": "boolean",
                "value": true
              }
            }
          },
          "severity": "block",
          "message": "Not locked",
          "overrideable": false
        }
      ],
      "actions": [
        {
          "kind": "mutate",
          "target": "isLocked",
          "expression": {
            "kind": "literal",
            "value": {
              "kind": "boolean",
              "value": false
            }
          }
        },
        {
          "kind": "mutate",
          "target": "concurrencyVersion",
          "expression": {
            "kind": "binary",
            "operator": "+",
            "left": {
              "kind": "member",
              "object": {
                "kind": "identifier",
                "name": "self"
              },
              "property": "concurrencyVersion"
            },
            "right": {
              "kind": "literal",
              "value": {
                "kind": "number",
                "value": 1
              }
            }
          }
        },
        {
          "kind": "mutate",
          "target": "updatedAt",
          "expression": {
            "kind": "call",
            "callee": {
              "kind": "identifier",
              "name": "now"
            },
            "args": []
          }
        }
      ],
      "emits": [
        "WorkflowUnlocked"
      ]
    },
    {
      "name": "complete",
      "entity": "WorkflowInstance",
      "parameters": [],
      "guards": [],
      "constraints": [
        {
          "name": "canComplete",
          "code": "canComplete",
          "expression": {
            "kind": "binary",
            "operator": "in",
            "left": {
              "kind": "member",
              "object": {
                "kind": "identifier",
                "name": "self"
              },
              "property": "status"
            },
            "right": {
              "kind": "array",
              "elements": [
                {
                  "kind": "literal",
                  "value": {
                    "kind": "string",
                    "value": "active"
                  }
                },
                {
                  "kind": "literal",
                  "value": {
                    "kind": "string",
                    "value": "paused"
                  }
                }
              ]
            }
          },
          "severity": "block",
          "message": "Cannot complete workflow in current state",
          "overrideable": false
        }
      ],
      "actions": [
        {
          "kind": "mutate",
          "target": "status",
          "expression": {
            "kind": "literal",
            "value": {
              "kind": "string",
              "value": "completed"
            }
          }
        },
        {
          "kind": "mutate",
          "target": "updatedAt",
          "expression": {
            "kind": "call",
            "callee": {
              "kind": "identifier",
              "name": "now"
            },
            "args": []
          }
        }
      ],
      "emits": [
        "WorkflowCompleted"
      ]
    }
  ],
  "policies": []
}
