{
  "version": "1.0",
  "provenance": {
    "contentHash": "normalized-content-hash",
    "irHash": "5438f8f7e1a5ce3709f0a0227d71dccd1463abf2bed1026f9ba22c4004bb3f1b",
    "compilerVersion": "normalized-compiler-version",
    "schemaVersion": "1.0",
    "compiledAt": "2024-01-01T00:00:00.000Z"
  },
  "modules": [],
  "values": [],
  "entities": [
    {
      "name": "Timestampable",
      "properties": [
        {
          "name": "createdAt",
          "type": {
            "name": "string",
            "nullable": false
          },
          "defaultValue": {
            "kind": "string",
            "value": ""
          },
          "modifiers": []
        },
        {
          "name": "updatedAt",
          "type": {
            "name": "string",
            "nullable": false
          },
          "defaultValue": {
            "kind": "string",
            "value": ""
          },
          "modifiers": []
        }
      ],
      "computedProperties": [],
      "relationships": [],
      "commands": [],
      "constraints": [],
      "policies": []
    },
    {
      "name": "SoftDeletable",
      "properties": [
        {
          "name": "deletedAt",
          "type": {
            "name": "string",
            "nullable": false
          },
          "defaultValue": {
            "kind": "string",
            "value": ""
          },
          "modifiers": []
        }
      ],
      "computedProperties": [],
      "relationships": [],
      "commands": [
        "SoftDelete"
      ],
      "constraints": [],
      "policies": []
    },
    {
      "name": "Article",
      "properties": [
        {
          "name": "createdAt",
          "type": {
            "name": "string",
            "nullable": false
          },
          "defaultValue": {
            "kind": "string",
            "value": ""
          },
          "modifiers": []
        },
        {
          "name": "updatedAt",
          "type": {
            "name": "string",
            "nullable": false
          },
          "defaultValue": {
            "kind": "string",
            "value": ""
          },
          "modifiers": []
        },
        {
          "name": "deletedAt",
          "type": {
            "name": "string",
            "nullable": false
          },
          "defaultValue": {
            "kind": "string",
            "value": ""
          },
          "modifiers": []
        },
        {
          "name": "id",
          "type": {
            "name": "string",
            "nullable": false
          },
          "defaultValue": {
            "kind": "string",
            "value": ""
          },
          "modifiers": [
            "required"
          ]
        },
        {
          "name": "title",
          "type": {
            "name": "string",
            "nullable": false
          },
          "defaultValue": {
            "kind": "string",
            "value": ""
          },
          "modifiers": []
        }
      ],
      "computedProperties": [],
      "relationships": [],
      "commands": [
        "SoftDelete"
      ],
      "constraints": [],
      "policies": [],
      "mixins": [
        "Timestampable",
        "SoftDeletable"
      ]
    }
  ],
  "enums": [],
  "stores": [],
  "events": [
    {
      "name": "EntitySoftDeleted",
      "channel": "entity.soft_deleted",
      "payload": [
        {
          "name": "id",
          "type": {
            "name": "string",
            "nullable": false
          },
          "required": true
        }
      ]
    }
  ],
  "commands": [
    {
      "name": "SoftDelete",
      "entity": "SoftDeletable",
      "parameters": [],
      "guards": [],
      "constraints": [],
      "actions": [
        {
          "kind": "mutate",
          "target": "deletedAt",
          "expression": {
            "kind": "literal",
            "value": {
              "kind": "string",
              "value": "2024-01-01"
            }
          }
        }
      ],
      "emits": [
        "EntitySoftDeleted"
      ]
    }
  ],
  "policies": [],
  "reactions": []
}
